sandypackages/__init__.py
sandypackages/deepu.py
sandypackages/jaya.py
sandypackages/kiran.py
sandypackages/shaan.py
sandypackages-1.2.dist-info/LICENSE
sandypackages-1.2.dist-info/METADATA
sandypackages-1.2.dist-info/WHEEL
sandypackages-1.2.dist-info/top_level.txt
sandypackages-1.2.dist-info/RECORD
