Metadata-Version: 2.1
Name: sandypackages
Version: 1.2
Summary: Data_Analyst_PKG
Author: vishwanath,shantha,sandhya
Author-email: vishwa64@outlook.com
License: MIT
Classifier: Programming Language :: Python :: 3
Classifier: License :: OSI Approved :: MIT License
Classifier: Operating System :: OS Independent
Requires-Python: >=3.6
License-File: LICENSE
